setup.py
portify/__init__.py
portify/config.py
portify/converter.py
portify/filesystem.py
portify/release.py
portify/workers.py
portify.egg-info/PKG-INFO
portify.egg-info/SOURCES.txt
portify.egg-info/dependency_links.txt
portify.egg-info/requires.txt
portify.egg-info/top_level.txt
portify.egg-info/zip-safe
tests/__init__.py
tests/core.py
tests/test_all.py
tests/test_config.py
tests/test_converter.py
tests/test_filesystem.py
tests/test_logging.py
tests/test_workers.py
tests/utils25.py
tests/utils26.py
tests/workerdefn.py