Metadata-Version: 1.0
Name: portify
Version: 1.0
Summary: A recursive file conversion utility, aimed at making it easier to get OSS audio on to iPods
Home-page: UNKNOWN
Author: Andy Theyers
Author-email: andy.theyers@isotoma.com
License: UNKNOWN
Download-URL: http://github.com/offmessage/portify
Platform: UNKNOWN
Classifier: Development Status :: 5 - Production/Stable
Classifier: Intended Audience :: Developers
Classifier: License :: OSI Approved :: BSD License
Classifier: Operating System :: OS Independent
Classifier: Programming Language :: Python
Classifier: Topic :: Multimedia :: Sound/Audio :: Conversion
Classifier: Topic :: Software Development :: Libraries :: Python Modules
